telepathy/const.py
telepathy/telepathy.py
telepathy/utils.py
telepathy-2.3.4.dist-info/LICENSE.txt
telepathy-2.3.4.dist-info/METADATA
telepathy-2.3.4.dist-info/WHEEL
telepathy-2.3.4.dist-info/entry_points.txt
telepathy-2.3.4.dist-info/top_level.txt
telepathy-2.3.4.dist-info/RECORD
