Metadata-Version: 2.1
Name: telepathy
Version: 2.3.4
Summary: An OSINT toolkit for investigating Telegram chats.
Home-page: https://pypi.python.org/pypi/telepathy/
Author: Jordan Wildon
Author-email: j.wildon@pm.me
License: LICENSE.txt
Platform: UNKNOWN
License-File: LICENSE.txt
Requires-Dist: alive-progress (==2.4.1)
Requires-Dist: beautifulsoup4 (==4.11.1)
Requires-Dist: click (~=7.1.2)
Requires-Dist: colorama (~=0.4.3)
Requires-Dist: googletrans (==4.0.0rc1)
Requires-Dist: pandas
Requires-Dist: pprintpp (==0.4.0)
Requires-Dist: requests (~=2.28.1)
Requires-Dist: telethon (==1.36.0)
